ppmpy/__init__.py
ppmpy/_version.py
ppmpy/advection.py
ppmpy/eigen.py
ppmpy/euler.py
ppmpy/gravity.py
ppmpy/grid.py
ppmpy/initial_conditions.py
ppmpy/reconstruction.py
ppmpy/riemann_exact.py
ppmpy-1.0.2.dist-info/LICENSE
ppmpy-1.0.2.dist-info/METADATA
ppmpy-1.0.2.dist-info/WHEEL
ppmpy-1.0.2.dist-info/top_level.txt
ppmpy-1.0.2.dist-info/RECORD
