Metadata-Version: 2.1
Name: ppmpy
Version: 1.0.2
Summary: A PPM hydrodynamics solver written in python
Author: Michael Zingale
Author-email: michael.zingale@stonybrook.edu
License: BSD
Project-URL: Homepage, https://github.com/zingale/ppmpy
License-File: LICENSE
Requires-Dist: numpy
Requires-Dist: scipy
Requires-Dist: matplotlib
